{
 "auto": {
  "67601974d9da5c2bcc25f689": {}
 },
 "timer": {
  "6760195ed9da5c2bcc25f682": {
   "ozon": {
    "date": "2025-01-23T05:27:51.445Z",
    "type": "ozon",
    "typeSignal": "timer",
    "msg": "Озонатор запрещен"
   }
  }
 },
 "extralrm": {
  "6760195ed9da5c2bcc25f682": {
   "67602254d9da5c2bcc25f6c9": {
    "676022c3d9da5c2bcc25f6cd": {
     "date": "2025-01-24T11:33:51.376Z",
     "count": true,
     "code": "sensor",
     "typeSignal": "sensor",
     "msg": "Неисправность датчика",
     "title": "Секция 1. Темп. канала 2:",
     "buildingId": "6760195ed9da5c2bcc25f682"
    }
   },
   "alrClosed": {
    "date": "2025-01-24T12:34:28.071Z",
    "count": true,
    "code": "alrClosed",
    "type": "alr",
    "typeSignal": "critical",
    "msg": "Аварийное закрытие клапанов",
    "title": "",
    "buildingId": "6760195ed9da5c2bcc25f682"
   },
   "local": {
    "date": "2025-01-24T10:22:13.857Z",
    "count": true,
    "code": "local",
    "type": "",
    "typeSignal": "critical",
    "msg": "Управление переведено переключателем на щите",
    "title": "",
    "buildingId": "6760195ed9da5c2bcc25f682"
   }
  },
  "67601974d9da5c2bcc25f689": {}
 },
 "extra": {
  "6760195ed9da5c2bcc25f682": {
   "accel": {
    "on": {
     "date": "2025-01-24T13:28:25.128Z",
     "code": "on",
     "typeSignal": "info",
     "msg": "Режим работы разгонного вентилятора: Включен",
     "title": "",
     "buildingId": "6760195ed9da5c2bcc25f682"
    }
   },
   "67602254d9da5c2bcc25f6c9": {
    "connect": {
     "date": "2025-01-24T11:33:51.384Z",
     "code": "",
     "typeSignal": "info",
     "msg": "Модуль в сети",
     "title": "Секция 1:",
     "buildingId": "6760195ed9da5c2bcc25f682"
    }
   },
   "connect": {
    "date": "2025-01-24T11:33:51.384Z",
    "code": "",
    "typeSignal": "info",
    "msg": "Модуль в сети",
    "title": "",
    "buildingId": "6760195ed9da5c2bcc25f682"
   }
  }
 },
 "achieve": {},
 "module": {
  "67601974d9da5c2bcc25f689": {
   "677fc905a61e120c0c75607f": {
    "date": "2025-01-24T13:52:15.670Z",
    "count": true,
    "code": "module",
    "typeSignal": "critical",
    "msg": "Нет связи",
    "title": "Модуль МК210-301 (IP 192.168.1.228:502):",
    "buildingId": "67601974d9da5c2bcc25f689"
   }
  }
 },
 "debounce": {}
}